{
	"class" : {
		 },
	"instance" : {
		"assignmentOp" : "tv 3/28/2009 13:35",
		"createSymbol:" : "TestRunner 10/21/2009 09:00",
		"doesNotUnderstand:" : "tv 4/2/2009 16:10",
		"initialize" : "TestRunner 10/21/2009 08:28",
		"initializeAnnotation" : "tv 3/30/2009 13:31",
		"initializeArray" : "tv 3/28/2009 13:23",
		"initializeArrayConstant" : "tv 3/28/2009 13:23",
		"initializeAssignmentExpressions" : "tv 3/28/2009 13:35",
		"initializeBar" : "tv 4/2/2009 15:38",
		"initializeBinaryExpression" : "TestRunner 10/21/2009 08:34",
		"initializeBinaryMessageDefinition" : "TestRunner 10/21/2009 08:34",
		"initializeBinaryMessageExpression" : "TestRunner 10/21/2009 08:34",
		"initializeBinaryObjectDescription" : "tv 3/28/2009 15:28",
		"initializeBinarySelector" : "TestRunner 10/21/2009 08:53",
		"initializeBlock" : "tv 3/28/2009 18:18",
		"initializeBlockArguments" : "tv 3/28/2009 13:23",
		"initializeBraceExpression" : "tv 3/28/2009 13:23",
		"initializeCapitalIdentifier" : "tv 3/28/2009 13:23",
		"initializeCascadedMessageExpression" : "tv 3/30/2009 13:25",
		"initializeCharacter" : "tv 4/2/2009 15:39",
		"initializeCharacterConstant" : "tv 3/28/2009 13:23",
		"initializeCommentFormat" : "tv 3/28/2009 13:23",
		"initializeDecimalDigit" : "tv 4/2/2009 15:38",
		"initializeExpression" : "tv 3/28/2009 17:42",
		"initializeFinalExpression" : "tv 3/28/2009 13:23",
		"initializeIdentifier" : "tv 3/28/2009 13:23",
		"initializeKeyword" : "tv 3/28/2009 13:23",
		"initializeKeywordAnnotation" : "tv 3/30/2009 13:26",
		"initializeKeywordExpression" : "tv 3/28/2009 17:28",
		"initializeKeywordMessageExpression" : "tv 3/28/2009 17:21",
		"initializeKeywordsArguments" : "tv 3/28/2009 17:15",
		"initializeLetter" : "tv 4/2/2009 15:39",
		"initializeLiteral" : "tv 3/28/2009 13:23",
		"initializeLowercase" : "tv 4/2/2009 15:39",
		"initializeMessageExpression" : "tv 3/28/2009 19:17",
		"initializeMessagePattern" : "tv 3/28/2009 17:10",
		"initializeMethod" : "tv 3/28/2009 19:17",
		"initializeNumberConstant" : "tv 3/28/2009 13:23",
		"initializeParameterName" : "tv 3/28/2009 17:12",
		"initializePrimary" : "tv 3/28/2009 14:32",
		"initializePrimaryVariable" : "tv 3/28/2009 13:23",
		"initializeReturn" : "tv 3/28/2009 13:23",
		"initializeScopedExpression" : "tv 3/28/2009 13:23",
		"initializeSeparator" : "tv 4/2/2009 16:07",
		"initializeSpecialCharacter" : "tv 4/2/2009 15:39",
		"initializeStatements" : "tv 3/28/2009 13:23",
		"initializeString" : "tv 3/28/2009 13:23",
		"initializeStringConstant" : "tv 3/28/2009 13:23",
		"initializeSubExpression" : "tv 3/28/2009 13:23",
		"initializeSymbol" : "tv 3/28/2009 13:23",
		"initializeSymbolConstant" : "tv 3/28/2009 13:23",
		"initializeSymbolInArray" : "tv 3/28/2009 13:23",
		"initializeSymbolKeywords" : "tv 3/28/2009 13:23",
		"initializeTemporaries" : "tv 3/28/2009 13:23",
		"initializeUnaryAnnotation" : "tv 3/30/2009 13:29",
		"initializeUnaryExpression" : "tv 3/28/2009 15:08",
		"initializeUnaryMessageDefinition" : "tv 3/30/2009 10:55",
		"initializeUnaryMessageExpression" : "tv 3/28/2009 18:59",
		"initializeUnaryObjectDescription" : "tv 3/28/2009 15:29",
		"initializeUnarySelector" : "tv 3/28/2009 13:23",
		"initializeUppercase" : "tv 4/2/2009 15:39",
		"initializeVariableName" : "tv 3/28/2009 18:11",
		"injectBinaryObjectDescription" : "tv 3/28/2009 15:27",
		"injectCascadedMessageExpression" : "tv 3/28/2009 17:40",
		"injectMessageExpression" : "tv 3/28/2009 14:45",
		"injectPrimary" : "tv 3/28/2009 14:31",
		"parsers:" : "tv 3/28/2009 19:15",
		"preStoreBinaryObjectDescription" : "tv 3/28/2009 15:25",
		"preStoreCascadedMessageExpression" : "tv 3/28/2009 14:43",
		"preStoreMessageExpression" : "tv 3/28/2009 14:43",
		"preStorePrimary" : "tv 3/28/2009 14:24",
		"symbols" : "TestRunner 10/21/2009 08:33" } }
